AoikEnum-0.1.1.dist-info/DESCRIPTION.rst
AoikEnum-0.1.1.dist-info/METADATA
AoikEnum-0.1.1.dist-info/RECORD
AoikEnum-0.1.1.dist-info/WHEEL
AoikEnum-0.1.1.dist-info/metadata.json
AoikEnum-0.1.1.dist-info/top_level.txt
aoikenum/__init__.py
aoikenum/aoikenum.py
aoikenum/aoikenum_tests.py
